procprotect/__init__.py
procprotect/debugCheck.py
procprotect/main.py
procprotect/vmCheck.py
procprotect/lists/__init__.py
procprotect/lists/default_debugCheck.py
procprotect/lists/default_vmCheck.py
procprotect-0.1.15.dist-info/LICENSE
procprotect-0.1.15.dist-info/METADATA
procprotect-0.1.15.dist-info/WHEEL
procprotect-0.1.15.dist-info/top_level.txt
procprotect-0.1.15.dist-info/RECORD
