Metadata-Version: 2.1
Name: procprotect
Version: 0.1.15
Summary: A package to protect your app from debugging and other attacks.
Home-page: https://github.com/cookie0o
Author: cookie0_o
Author-email: cookie0o@protonmail.com
Classifier: Programming Language :: Python :: 3
Classifier: License :: OSI Approved :: MIT License
Classifier: Operating System :: OS Independent
Requires-Python: >=3.7
License-File: LICENSE
